celium_collateral-1.1.6.dist-info/licenses/LICENSE
celium_collateral_contracts/__init__.py
celium_collateral_contracts/abi.json
celium_collateral_contracts/address_conversion.py
celium_collateral_contracts/backup_state.py
celium_collateral_contracts/collateral_contract.py
celium_collateral_contracts/common.py
celium_collateral_contracts/deny_request.py
celium_collateral_contracts/deposit_collateral.py
celium_collateral_contracts/finalize_reclaim.py
celium_collateral_contracts/generate_commands.py
celium_collateral_contracts/generate_keypair.py
celium_collateral_contracts/get_balance.py
celium_collateral_contracts/get_collaterals.py
celium_collateral_contracts/get_current_block.py
celium_collateral_contracts/get_executor_collateral.py
celium_collateral_contracts/get_reclaim_requests.py
celium_collateral_contracts/reclaim_collateral.py
celium_collateral_contracts/slash_collateral.py
celium_collateral_contracts/verify_contract.py
celium_collateral-1.1.6.dist-info/METADATA
celium_collateral-1.1.6.dist-info/WHEEL
celium_collateral-1.1.6.dist-info/top_level.txt
celium_collateral-1.1.6.dist-info/RECORD
