Metadata-Version: 2.4
Name: celium-collateral
Version: 1.1.6
Summary: Collateral Smart Contract for Lium
Author-email: Waris <waris0609@outlook.com>
License: BSD 3-Clause License
Project-URL: Homepage, https://github.com/Datura-ai/celium-collateral-contracts
Project-URL: Source, https://github.com/Datura-ai/celium-collateral-contracts
Classifier: Programming Language :: Python :: 3
Classifier: License :: OSI Approved :: BSD License
Classifier: Operating System :: OS Independent
Requires-Python: <3.13,>=3.11
License-File: LICENSE
Requires-Dist: web3>=6.0.0
Requires-Dist: requests>=2.32.3
Requires-Dist: eth-utils==2.2.2
Requires-Dist: scalecodec>=1.2.11
Dynamic: license-file
